<?xml version="1.0"?>
<!DOCTYPE hibernate-mapping PUBLIC "-//Hibernate/Hibernate Mapping DTD 3.0//EN"
"http://hibernate.sourceforge.net/hibernate-mapping-3.0.dtd">
<!-- Generated 04-ene-2013 11:21:17 by Hibernate Tools 3.4.0.CR1 -->
<hibernate-mapping>
    <class name="modelo.ServicioPosicionamiento" table="ServicioPosicionamiento" catalog="procuidado">
        <id name="identificador" type="int">
            <column name="identificador" />
            <generator class="foreign">
                <param name="property">servicio</param>
            </generator>
        </id>
        <one-to-one name="servicio" class="modelo.Servicio" constrained="true"></one-to-one>
        <property name="horaEstanciaFin" type="string">
            <column name="horaEstanciaFin" length="50" />
        </property>
        <property name="horaEstanciaInicio" type="string">
            <column name="horaEstanciaInicio" length="50" />
        </property>
    </class>
</hibernate-mapping>
